aconfig/__init__.py
aconfig/aconfig.py
alchemy_config-1.1.3.dist-info/LICENSE
alchemy_config-1.1.3.dist-info/METADATA
alchemy_config-1.1.3.dist-info/WHEEL
alchemy_config-1.1.3.dist-info/top_level.txt
alchemy_config-1.1.3.dist-info/RECORD
