Metadata-Version: 2.1
Name: alchemy-config
Version: 1.1.3
Summary: Configuration framework in Python for general configuration use.
Home-page: https://github.com/IBM/alchemy-config
Author: Gabe Goodhart
Author-email: gabe.l.hart@gmail.com
License: MIT
Keywords: config
Platform: UNKNOWN
License-File: LICENSE
Requires-Dist: PyYAML (>=5.3.1)
